status_manager/__init__.py
status_manager/main.py
status_manager-1.0.3.dist-info/LICENSE
status_manager-1.0.3.dist-info/METADATA
status_manager-1.0.3.dist-info/WHEEL
status_manager-1.0.3.dist-info/top_level.txt
status_manager-1.0.3.dist-info/RECORD
