Metadata-Version: 2.1
Name: status-manager
Version: 1.0.3
Summary: simple and useful status manager for bulk computations
Author: Javad Saeedi
Author-email: <j.saeedi.edu@gmail.com>
Keywords: status-manager,status,computation
Classifier: Development Status :: 1 - Planning
Classifier: Intended Audience :: Developers
Classifier: Programming Language :: Python :: 3
Classifier: Operating System :: Unix
Classifier: Operating System :: MacOS :: MacOS X
Classifier: Operating System :: Microsoft :: Windows
License-File: LICENSE
